pacotepip/__init__.py
pacotepip/main.py
pacotepip/cmd/__init__.py
pacotepip/cmd/about.txt
pacotepip/cmd/architecture.txt
pacotepip/cmd/help.txt
pacotepip/cmd/list.txt
pacotepip/modules/__init__.py
pacotepip/modules/data_cleaning.py
pacotepip/modules/doc_generation.py
pacotepip/modules/usable.py
pacotepip-1.0.0.dist-info/LICENSE
pacotepip-1.0.0.dist-info/METADATA
pacotepip-1.0.0.dist-info/WHEEL
pacotepip-1.0.0.dist-info/entry_points.txt
pacotepip-1.0.0.dist-info/top_level.txt
pacotepip-1.0.0.dist-info/RECORD
