Metadata-Version: 2.1
Name: pacotepip
Version: 1.0.0
Summary: Pacote de teste
Home-page: https://github.com/diogjunior100/pacotepip.git
Author: Bruno, Igor e Diógenes
Author-email: bruno.martval@gmail.com
License: MIT
Keywords: pacotepip
Platform: UNKNOWN
Classifier: Programming Language :: Python :: 3
Classifier: License :: OSI Approved :: MIT License
Classifier: Operating System :: OS Independent
License-File: LICENSE
Requires-Dist: mdpdf (==0.0.18)
Requires-Dist: pandas (==1.5.2)
